pyhoptico/__init__.py
pyhoptico/client.py
pyhoptico/client_test.py
pyhoptico-0.2.0.dist-info/LICENSE.txt
pyhoptico-0.2.0.dist-info/METADATA
pyhoptico-0.2.0.dist-info/WHEEL
pyhoptico-0.2.0.dist-info/RECORD
